{
  "eventos": [
    {
      "id": "primera-division-juventud-vs-torque",
      "hora_inicio": "08:00",
      "hora_fin": "09:54",
      "adicionales": 3,
      "estado": "auto"
    },
    {
      "id": "primera-division-danubio-vs-nacional",
      "hora_inicio": "13:00",
      "hora_fin": "14:52",
      "adicionales": 4,
      "estado": "auto"
    },
    {
      "id": "amistoso-benfica-vs-flamengo",
      "hora_inicio": "13:30",
      "hora_fin": "15:22",
      "adicionales": 4,
      "estado": "auto"
    },
    {
      "id": "copa-de-chile-magallanes-vs-audax-italiano",
      "hora_inicio": "14:00",
      "hora_fin": "15:54",
      "adicionales": 6,
      "estado": "auto"
    },
    {
      "id": "ufc-conor-mcgregor-vs-max-holloway",
      "hora_inicio": "14:00",
      "hora_fin": "16:00",
      "adicionales": 0,
      "estado": "auto"
    },
    {
      "id": "nba-summer-league-pelicans-vs-hornets",
      "hora_inicio": "15:00",
      "hora_fin": "17:00",
      "adicionales": 6,
      "estado": "auto"
    },
    {
      "id": "copa-mundial-de-la-fifa-noruega-vs-inglaterra-4tos-de-final",
      "hora_inicio": "16:00",
      "hora_fin": "17:54",
      "adicionales": 6,
      "estado": "auto"
    },
    {
      "id": "primera-division-wanderers-vs-progreso",
      "hora_inicio": "16:00",
      "hora_fin": "15:52",
      "adicionales": 4,
      "estado": "auto"
    },
    {
      "id": "copa-de-chile-san-luis-vs-universidad-catolica",
      "hora_inicio": "16:30",
      "hora_fin": "18:22",
      "adicionales": 6,
      "estado": "auto"
    },
    {
      "id": "nba-summer-league-knicks-vs-spurs",
      "hora_inicio": "17:00",
      "hora_fin": "19:00",
      "adicionales": 0,
      "estado": "auto"
    },
    {
      "id": "nba-summer-league-hawks-vs-nets",
      "hora_inicio": "19:00",
      "hora_fin": "21:00",
      "adicionales": 0,
      "estado": "auto"
    },
    {
      "id": "copa-mundial-de-la-fifa-argentina-vs-suiza-4tos-de-final",
      "hora_inicio": "20:00",
      "hora_fin": "21:54",
      "adicionales": 6,
      "estado": "auto"
    },
    {
      "id": "nba-summer-league-lakers-vs-mavericks",
      "hora_inicio": "21:00",
      "hora_fin": "23:00",
      "adicionales": 9,
      "estado": "auto"
    }
  ]
}
